{
    "packages": {
        "ucf/ucf-wordpress-theme": [
            {
                "name": "ucf/ucf-wordpress-theme",
                "version": "v0.10.0",
                "version_normalized": "0.10.0.0",
                "source": {
                    "type": "git",
                    "url": "https://github.com/UCF/UCF-WordPress-Theme.git",
                    "reference": "11d647892c2cce42dea148c99703988d04a5e583"
                },
                "dist": {
                    "type": "zip",
                    "url": "https://api.github.com/repos/UCF/UCF-WordPress-Theme/zipball/11d647892c2cce42dea148c99703988d04a5e583",
                    "reference": "11d647892c2cce42dea148c99703988d04a5e583",
                    "shasum": ""
                },
                "require": {
                    "composer/installers": "~1.0"
                },
                "time": "2024-03-05T14:56:53+00:00",
                "type": "wordpress-theme",
                "description": "A generic, responsive WordPress theme for UCF websites, built off of the Athena Framework. Suitable as a standalone theme or as a parent theme.",
                "support": {
                    "source": "https://github.com/UCF/UCF-WordPress-Theme/tree/v0.10.0",
                    "issues": "https://github.com/UCF/UCF-WordPress-Theme/issues"
                }
            },
            {
                "name": "ucf/ucf-wordpress-theme",
                "version": "v0.11.0",
                "version_normalized": "0.11.0.0",
                "source": {
                    "type": "git",
                    "url": "https://github.com/UCF/UCF-WordPress-Theme.git",
                    "reference": "2ae14c11eca940afb0dc9ac96bf47f04fc9ad62a"
                },
                "dist": {
                    "type": "zip",
                    "url": "https://api.github.com/repos/UCF/UCF-WordPress-Theme/zipball/2ae14c11eca940afb0dc9ac96bf47f04fc9ad62a",
                    "reference": "2ae14c11eca940afb0dc9ac96bf47f04fc9ad62a",
                    "shasum": ""
                },
                "require": {
                    "composer/installers": "~1.0"
                },
                "time": "2024-04-30T17:38:29+00:00",
                "type": "wordpress-theme",
                "description": "A generic, responsive WordPress theme for UCF websites, built off of the Athena Framework. Suitable as a standalone theme or as a parent theme.",
                "support": {
                    "source": "https://github.com/UCF/UCF-WordPress-Theme/tree/v0.11.0",
                    "issues": "https://github.com/UCF/UCF-WordPress-Theme/issues"
                }
            },
            {
                "name": "ucf/ucf-wordpress-theme",
                "version": "v0.7.7",
                "version_normalized": "0.7.7.0",
                "source": {
                    "type": "git",
                    "url": "https://github.com/UCF/UCF-WordPress-Theme.git",
                    "reference": "612487aa30b97928bec4a4311a23d1f25b4ea100"
                },
                "dist": {
                    "type": "zip",
                    "url": "https://api.github.com/repos/UCF/UCF-WordPress-Theme/zipball/612487aa30b97928bec4a4311a23d1f25b4ea100",
                    "reference": "612487aa30b97928bec4a4311a23d1f25b4ea100",
                    "shasum": ""
                },
                "require": {
                    "composer/installers": "~1.0"
                },
                "time": "2023-03-21T20:11:10+00:00",
                "type": "wordpress-theme",
                "description": "A generic, responsive WordPress theme for UCF websites, built off of the Athena Framework. Suitable as a standalone theme or as a parent theme.",
                "support": {
                    "source": "https://github.com/UCF/UCF-WordPress-Theme/tree/v0.7.7",
                    "issues": "https://github.com/UCF/UCF-WordPress-Theme/issues"
                }
            },
            {
                "name": "ucf/ucf-wordpress-theme",
                "version": "v0.8.0",
                "version_normalized": "0.8.0.0",
                "source": {
                    "type": "git",
                    "url": "https://github.com/UCF/UCF-WordPress-Theme.git",
                    "reference": "c671635392453cb5a748eef7aa7d8e2b98258da7"
                },
                "dist": {
                    "type": "zip",
                    "url": "https://api.github.com/repos/UCF/UCF-WordPress-Theme/zipball/c671635392453cb5a748eef7aa7d8e2b98258da7",
                    "reference": "c671635392453cb5a748eef7aa7d8e2b98258da7",
                    "shasum": ""
                },
                "require": {
                    "composer/installers": "~1.0"
                },
                "time": "2023-05-24T20:15:14+00:00",
                "type": "wordpress-theme",
                "description": "A generic, responsive WordPress theme for UCF websites, built off of the Athena Framework. Suitable as a standalone theme or as a parent theme.",
                "support": {
                    "source": "https://github.com/UCF/UCF-WordPress-Theme/tree/v0.8.0",
                    "issues": "https://github.com/UCF/UCF-WordPress-Theme/issues"
                }
            },
            {
                "name": "ucf/ucf-wordpress-theme",
                "version": "v0.9.0",
                "version_normalized": "0.9.0.0",
                "source": {
                    "type": "git",
                    "url": "https://github.com/UCF/UCF-WordPress-Theme.git",
                    "reference": "b16dcd68dc098e71d1191dbde9ed416aabd3184e"
                },
                "dist": {
                    "type": "zip",
                    "url": "https://api.github.com/repos/UCF/UCF-WordPress-Theme/zipball/b16dcd68dc098e71d1191dbde9ed416aabd3184e",
                    "reference": "b16dcd68dc098e71d1191dbde9ed416aabd3184e",
                    "shasum": ""
                },
                "require": {
                    "composer/installers": "~1.0"
                },
                "time": "2024-02-22T18:15:31+00:00",
                "type": "wordpress-theme",
                "description": "A generic, responsive WordPress theme for UCF websites, built off of the Athena Framework. Suitable as a standalone theme or as a parent theme.",
                "support": {
                    "source": "https://github.com/UCF/UCF-WordPress-Theme/tree/v0.9.0",
                    "issues": "https://github.com/UCF/UCF-WordPress-Theme/issues"
                }
            },
            {
                "name": "ucf/ucf-wordpress-theme",
                "version": "v0.9.1",
                "version_normalized": "0.9.1.0",
                "source": {
                    "type": "git",
                    "url": "https://github.com/UCF/UCF-WordPress-Theme.git",
                    "reference": "63a722dde539d1bc778287e8e8a7dcc445c97141"
                },
                "dist": {
                    "type": "zip",
                    "url": "https://api.github.com/repos/UCF/UCF-WordPress-Theme/zipball/63a722dde539d1bc778287e8e8a7dcc445c97141",
                    "reference": "63a722dde539d1bc778287e8e8a7dcc445c97141",
                    "shasum": ""
                },
                "require": {
                    "composer/installers": "~1.0"
                },
                "time": "2024-02-26T20:30:34+00:00",
                "type": "wordpress-theme",
                "description": "A generic, responsive WordPress theme for UCF websites, built off of the Athena Framework. Suitable as a standalone theme or as a parent theme.",
                "support": {
                    "source": "https://github.com/UCF/UCF-WordPress-Theme/tree/v0.9.1",
                    "issues": "https://github.com/UCF/UCF-WordPress-Theme/issues"
                }
            },
            {
                "name": "ucf/ucf-wordpress-theme",
                "version": "v0.9.2",
                "version_normalized": "0.9.2.0",
                "source": {
                    "type": "git",
                    "url": "https://github.com/UCF/UCF-WordPress-Theme.git",
                    "reference": "4912760755b27db2f7c8ee64b0bf59cfb08cdd65"
                },
                "dist": {
                    "type": "zip",
                    "url": "https://api.github.com/repos/UCF/UCF-WordPress-Theme/zipball/4912760755b27db2f7c8ee64b0bf59cfb08cdd65",
                    "reference": "4912760755b27db2f7c8ee64b0bf59cfb08cdd65",
                    "shasum": ""
                },
                "require": {
                    "composer/installers": "~1.0"
                },
                "time": "2024-02-27T15:10:10+00:00",
                "type": "wordpress-theme",
                "description": "A generic, responsive WordPress theme for UCF websites, built off of the Athena Framework. Suitable as a standalone theme or as a parent theme.",
                "support": {
                    "source": "https://github.com/UCF/UCF-WordPress-Theme/tree/v0.9.2",
                    "issues": "https://github.com/UCF/UCF-WordPress-Theme/issues"
                }
            },
            {
                "name": "ucf/ucf-wordpress-theme",
                "version": "v1.0.0",
                "version_normalized": "1.0.0.0",
                "source": {
                    "type": "git",
                    "url": "https://github.com/UCF/UCF-WordPress-Theme.git",
                    "reference": "9e88509f4b3a7a72988976783a9b8ca9f1eded25"
                },
                "dist": {
                    "type": "zip",
                    "url": "https://api.github.com/repos/UCF/UCF-WordPress-Theme/zipball/9e88509f4b3a7a72988976783a9b8ca9f1eded25",
                    "reference": "9e88509f4b3a7a72988976783a9b8ca9f1eded25",
                    "shasum": ""
                },
                "require": {
                    "composer/installers": "~1.0"
                },
                "time": "2024-04-30T15:46:27+00:00",
                "type": "wordpress-theme",
                "description": "A generic, responsive WordPress theme for UCF websites, built off of the Athena Framework. Suitable as a standalone theme or as a parent theme.",
                "support": {
                    "source": "https://github.com/UCF/UCF-WordPress-Theme/tree/v1.0.0",
                    "issues": "https://github.com/UCF/UCF-WordPress-Theme/issues"
                }
            }
        ]
    }
}
